{
    "keep": {
        "days": true,
        "amount": 90
    },
    "auditLog": "C:\\Users\\MIGUEL\\Documents\\Proyectos-Cursor\\biblioteca-xonler-main\\logs\\.978195b1f072e1d57a64cd6d34430570f4ba6297-audit.json",
    "files": [
        {
            "date": 1759466703960,
            "name": "C:\\Users\\MIGUEL\\Documents\\Proyectos-Cursor\\biblioteca-xonler-main\\logs\\security-2025-10-02.log",
            "hash": "66285c7f8268f91d6b20b7dfb9dbddf51392029e5e6bccea4df8e129daec70ef"
        },
        {
            "date": 1759467600599,
            "name": "C:\\Users\\MIGUEL\\Documents\\Proyectos-Cursor\\biblioteca-xonler-main\\logs\\security-2025-10-03.log",
            "hash": "539dcd6955cc16a70d66265e8b31c95b530fef8e15cf12f4f152d4fa0ab75001"
        },
        {
            "date": 1759595821195,
            "name": "C:\\Users\\MIGUEL\\Documents\\Proyectos-Cursor\\biblioteca-xonler-main\\logs\\security-2025-10-04.log",
            "hash": "373823a4c215ae26098a9d281eddf6c6531620db28246f4a900d955d872dbf2c"
        },
        {
            "date": 1759684286145,
            "name": "C:\\Users\\MIGUEL\\Documents\\Proyectos-Cursor\\biblioteca-xonler-main\\logs\\security-2025-10-05.log",
            "hash": "10f9c420ab6fdb977d4f32b9646c815fde4320826c7281152040a66e9d4dfcdf"
        },
        {
            "date": 1759766043839,
            "name": "C:\\Users\\MIGUEL\\Documents\\Proyectos-Cursor\\biblioteca-xonler-main\\logs\\security-2025-10-06.log",
            "hash": "2c3b5a3138984507c7cccf2b23bf5ab2a4b9f63224bade0063821e3488d79966"
        }
    ],
    "hashType": "sha256"
}